odoo/addons/partner_vat_required/README.rst
odoo/addons/partner_vat_required/__init__.py
odoo/addons/partner_vat_required/__manifest__.py
odoo/addons/partner_vat_required/models/__init__.py
odoo/addons/partner_vat_required/models/res_partner.py
odoo/addons/partner_vat_required/static/description/icon.png
odoo_addon_partner_vat_required-15.0.1.0.0.3.dist-info/METADATA
odoo_addon_partner_vat_required-15.0.1.0.0.3.dist-info/WHEEL
odoo_addon_partner_vat_required-15.0.1.0.0.3.dist-info/top_level.txt
odoo_addon_partner_vat_required-15.0.1.0.0.3.dist-info/RECORD
