Metadata-Version: 2.1
Name: odoo-addon-partner_vat_required
Version: 15.0.1.0.0.3
Summary: VAT required in contacts.
Home-page: https://github.com/sygel-technology/sy-partner-contact
Author: Sygel
License: AGPL-3
Classifier: Programming Language :: Python
Classifier: Framework :: Odoo
Classifier: Framework :: Odoo :: 15.0
Classifier: License :: OSI Approved :: GNU Affero General Public License v3
Requires-Python: >=3.8
Requires-Dist: odoo<15.1dev,>=15.0a
